quicks/__init__.py
quicks/__main__.py
quicks/cli/__init__.py
quicks/cli/main.py
quicks/core.py
quicks/exceptions.py
quicks-0.0.6.dist-info/LICENSE
quicks-0.0.6.dist-info/METADATA
quicks-0.0.6.dist-info/WHEEL
quicks-0.0.6.dist-info/entry_points.txt
quicks-0.0.6.dist-info/RECORD
